rex_utils/__init__.py
rex_utils/structs.py
rex_utils/utils.py
rex_utils-0.1.2.dist-info/WHEEL
rex_utils-0.1.2.dist-info/METADATA
rex_utils-0.1.2.dist-info/RECORD
