Metadata-Version: 2.3
Name: rex-utils
Version: 0.1.2
Summary: Python utilities for writing Rex native drivers
Requires-Dist: pydantic>=2.12.3
Requires-Dist: numpy>=2.3.1
Requires-Dist: pandas>=2.3.0
Requires-Dist: plotly>=6.3.0
Requires-Dist: polars>=1.31.0
Requires-Dist: pyarrow>=21.0.0
Requires-Dist: pytest>=8.4.1
Requires-Dist: toml>=0.10.2
Requires-Python: >=3.13
